database_automation/__init__.py
database_automation/mongo_crud.py
db_automation825-0.0.6.dist-info/licenses/LICENSE
db_automation825-0.0.6.dist-info/METADATA
db_automation825-0.0.6.dist-info/WHEEL
db_automation825-0.0.6.dist-info/top_level.txt
db_automation825-0.0.6.dist-info/RECORD
